{
    "level":  48,
    "name":  "Desert Level 48",
    "timeBonusSeconds":  71,
    "tiles":  [
                  {
                      "id":  "L48_T000",
                      "type":  "star",
                      "x":  0.137,
                      "y":  0.114,
                      "layer":  0
                  },
                  {
                      "id":  "L48_T001",
                      "type":  "shell",
                      "x":  0.307,
                      "y":  0.109,
                      "layer":  0
                  },
                  {
                      "id":  "L48_T002",
                      "type":  "star",
                      "x":  0.43,
                      "y":  0.119,
                      "layer":  0
                  },
                  {
                      "id":  "L48_T003",
                      "type":  "shell",
                      "x":  0.586,
                      "y":  0.111,
                      "layer":  0
                  },
                  {
                      "id":  "L48_T004",
                      "type":  "gem",
                      "x":  0.701,
                      "y":  0.124,
                      "layer":  0
                  },
                  {
                      "id":  "L48_T005",
                      "type":  "candy",
                      "x":  0.86,
                      "y":  0.13,
                      "layer":  0
                  },
                  {
                      "id":  "L48_T006",
                      "type":  "leaf",
                      "x":  0.155,
                      "y":  0.328,
                      "layer":  0
                  },
                  {
                      "id":  "L48_T007",
                      "type":  "leaf",
                      "x":  0.279,
                      "y":  0.327,
                      "layer":  0
                  },
                  {
                      "id":  "L48_T008",
                      "type":  "moon",
                      "x":  0.431,
                      "y":  0.344,
                      "layer":  0
                  },
                  {
                      "id":  "L48_T009",
                      "type":  "banana",
                      "x":  0.557,
                      "y":  0.347,
                      "layer":  0
                  },
                  {
                      "id":  "L48_T010",
                      "type":  "drop",
                      "x":  0.713,
                      "y":  0.335,
                      "layer":  0
                  },
                  {
                      "id":  "L48_T011",
                      "type":  "heart",
                      "x":  0.854,
                      "y":  0.34,
                      "layer":  0
                  },
                  {
                      "id":  "L48_T012",
                      "type":  "star",
                      "x":  0.145,
                      "y":  0.532,
                      "layer":  0
                  },
                  {
                      "id":  "L48_T013",
                      "type":  "moon",
                      "x":  0.301,
                      "y":  0.543,
                      "layer":  0
                  },
                  {
                      "id":  "L48_T014",
                      "type":  "heart",
                      "x":  0.429,
                      "y":  0.551,
                      "layer":  0
                  },
                  {
                      "id":  "L48_T015",
                      "type":  "flower",
                      "x":  0.172,
                      "y":  0.129,
                      "layer":  1
                  },
                  {
                      "id":  "L48_T016",
                      "type":  "shell",
                      "x":  0.312,
                      "y":  0.137,
                      "layer":  1
                  },
                  {
                      "id":  "L48_T017",
                      "type":  "leaf",
                      "x":  0.448,
                      "y":  0.117,
                      "layer":  1
                  },
                  {
                      "id":  "L48_T018",
                      "type":  "gem",
                      "x":  0.579,
                      "y":  0.138,
                      "layer":  1
                  },
                  {
                      "id":  "L48_T019",
                      "type":  "heart",
                      "x":  0.727,
                      "y":  0.137,
                      "layer":  1
                  },
                  {
                      "id":  "L48_T020",
                      "type":  "berry",
                      "x":  0.848,
                      "y":  0.124,
                      "layer":  1
                  },
                  {
                      "id":  "L48_T021",
                      "type":  "clover",
                      "x":  0.169,
                      "y":  0.334,
                      "layer":  1
                  },
                  {
                      "id":  "L48_T022",
                      "type":  "gem",
                      "x":  0.291,
                      "y":  0.334,
                      "layer":  1
                  },
                  {
                      "id":  "L48_T023",
                      "type":  "drop",
                      "x":  0.435,
                      "y":  0.349,
                      "layer":  1
                  },
                  {
                      "id":  "L48_T024",
                      "type":  "candy",
                      "x":  0.585,
                      "y":  0.35,
                      "layer":  1
                  },
                  {
                      "id":  "L48_T025",
                      "type":  "leaf",
                      "x":  0.736,
                      "y":  0.335,
                      "layer":  1
                  },
                  {
                      "id":  "L48_T026",
                      "type":  "clover",
                      "x":  0.856,
                      "y":  0.336,
                      "layer":  1
                  },
                  {
                      "id":  "L48_T027",
                      "type":  "clover",
                      "x":  0.152,
                      "y":  0.561,
                      "layer":  1
                  },
                  {
                      "id":  "L48_T028",
                      "type":  "berry",
                      "x":  0.31,
                      "y":  0.55,
                      "layer":  1
                  },
                  {
                      "id":  "L48_T029",
                      "type":  "banana",
                      "x":  0.453,
                      "y":  0.558,
                      "layer":  1
                  },
                  {
                      "id":  "L48_T030",
                      "type":  "sun",
                      "x":  0.181,
                      "y":  0.144,
                      "layer":  2
                  },
                  {
                      "id":  "L48_T031",
                      "type":  "candy",
                      "x":  0.323,
                      "y":  0.147,
                      "layer":  2
                  },
                  {
                      "id":  "L48_T032",
                      "type":  "sun",
                      "x":  0.468,
                      "y":  0.145,
                      "layer":  2
                  },
                  {
                      "id":  "L48_T033",
                      "type":  "moon",
                      "x":  0.578,
                      "y":  0.158,
                      "layer":  2
                  },
                  {
                      "id":  "L48_T034",
                      "type":  "gem",
                      "x":  0.74,
                      "y":  0.135,
                      "layer":  2
                  },
                  {
                      "id":  "L48_T035",
                      "type":  "carrot",
                      "x":  0.86,
                      "y":  0.155,
                      "layer":  2
                  },
                  {
                      "id":  "L48_T036",
                      "type":  "carrot",
                      "x":  0.164,
                      "y":  0.357,
                      "layer":  2
                  },
                  {
                      "id":  "L48_T037",
                      "type":  "flower",
                      "x":  0.326,
                      "y":  0.353,
                      "layer":  2
                  },
                  {
                      "id":  "L48_T038",
                      "type":  "apple",
                      "x":  0.468,
                      "y":  0.356,
                      "layer":  2
                  },
                  {
                      "id":  "L48_T039",
                      "type":  "carrot",
                      "x":  0.595,
                      "y":  0.349,
                      "layer":  2
                  },
                  {
                      "id":  "L48_T040",
                      "type":  "sun",
                      "x":  0.742,
                      "y":  0.348,
                      "layer":  2
                  },
                  {
                      "id":  "L48_T041",
                      "type":  "candy",
                      "x":  0.86,
                      "y":  0.367,
                      "layer":  2
                  },
                  {
                      "id":  "L48_T042",
                      "type":  "star",
                      "x":  0.185,
                      "y":  0.573,
                      "layer":  2
                  },
                  {
                      "id":  "L48_T043",
                      "type":  "leaf",
                      "x":  0.298,
                      "y":  0.573,
                      "layer":  2
                  },
                  {
                      "id":  "L48_T044",
                      "type":  "flower",
                      "x":  0.451,
                      "y":  0.558,
                      "layer":  2
                  },
                  {
                      "id":  "L48_T045",
                      "type":  "banana",
                      "x":  0.179,
                      "y":  0.147,
                      "layer":  3
                  },
                  {
                      "id":  "L48_T046",
                      "type":  "gem",
                      "x":  0.342,
                      "y":  0.145,
                      "layer":  3
                  },
                  {
                      "id":  "L48_T047",
                      "type":  "moon",
                      "x":  0.485,
                      "y":  0.16,
                      "layer":  3
                  },
                  {
                      "id":  "L48_T048",
                      "type":  "drop",
                      "x":  0.606,
                      "y":  0.143,
                      "layer":  3
                  },
                  {
                      "id":  "L48_T049",
                      "type":  "star",
                      "x":  0.738,
                      "y":  0.162,
                      "layer":  3
                  },
                  {
                      "id":  "L48_T050",
                      "type":  "flower",
                      "x":  0.86,
                      "y":  0.151,
                      "layer":  3
                  },
                  {
                      "id":  "L48_T051",
                      "type":  "candy",
                      "x":  0.203,
                      "y":  0.365,
                      "layer":  3
                  },
                  {
                      "id":  "L48_T052",
                      "type":  "heart",
                      "x":  0.337,
                      "y":  0.355,
                      "layer":  3
                  },
                  {
                      "id":  "L48_T053",
                      "type":  "berry",
                      "x":  0.483,
                      "y":  0.38,
                      "layer":  3
                  },
                  {
                      "id":  "L48_T054",
                      "type":  "flower",
                      "x":  0.601,
                      "y":  0.382,
                      "layer":  3
                  },
                  {
                      "id":  "L48_T055",
                      "type":  "apple",
                      "x":  0.754,
                      "y":  0.361,
                      "layer":  3
                  },
                  {
                      "id":  "L48_T056",
                      "type":  "moon",
                      "x":  0.86,
                      "y":  0.37,
                      "layer":  3
                  },
                  {
                      "id":  "L48_T057",
                      "type":  "shell",
                      "x":  0.197,
                      "y":  0.582,
                      "layer":  3
                  },
                  {
                      "id":  "L48_T058",
                      "type":  "star",
                      "x":  0.333,
                      "y":  0.596,
                      "layer":  3
                  },
                  {
                      "id":  "L48_T059",
                      "type":  "moon",
                      "x":  0.478,
                      "y":  0.576,
                      "layer":  3
                  },
                  {
                      "id":  "L48_T060",
                      "type":  "carrot",
                      "x":  0.196,
                      "y":  0.168,
                      "layer":  4
                  },
                  {
                      "id":  "L48_T061",
                      "type":  "apple",
                      "x":  0.339,
                      "y":  0.17,
                      "layer":  4
                  },
                  {
                      "id":  "L48_T062",
                      "type":  "leaf",
                      "x":  0.493,
                      "y":  0.173,
                      "layer":  4
                  },
                  {
                      "id":  "L48_T063",
                      "type":  "carrot",
                      "x":  0.634,
                      "y":  0.155,
                      "layer":  4
                  },
                  {
                      "id":  "L48_T064",
                      "type":  "shell",
                      "x":  0.758,
                      "y":  0.159,
                      "layer":  4
                  },
                  {
                      "id":  "L48_T065",
                      "type":  "carrot",
                      "x":  0.86,
                      "y":  0.178,
                      "layer":  4
                  },
                  {
                      "id":  "L48_T066",
                      "type":  "candy",
                      "x":  0.186,
                      "y":  0.392,
                      "layer":  4
                  },
                  {
                      "id":  "L48_T067",
                      "type":  "heart",
                      "x":  0.326,
                      "y":  0.377,
                      "layer":  4
                  },
                  {
                      "id":  "L48_T068",
                      "type":  "gem",
                      "x":  0.468,
                      "y":  0.38,
                      "layer":  4
                  },
                  {
                      "id":  "L48_T069",
                      "type":  "shell",
                      "x":  0.6,
                      "y":  0.389,
                      "layer":  4
                  },
                  {
                      "id":  "L48_T070",
                      "type":  "flower",
                      "x":  0.764,
                      "y":  0.373,
                      "layer":  4
                  },
                  {
                      "id":  "L48_T071",
                      "type":  "heart",
                      "x":  0.86,
                      "y":  0.382,
                      "layer":  4
                  }
              ]
}
